reaction_query-0.3.1.dist-info/METADATA
reaction_query-0.3.1.dist-info/WHEEL
reaction_query/__init__.py
reaction_query/reaction_query.cpython-312-darwin.so
reaction_query-0.3.1.dist-info/RECORD
