Metadata-Version: 2.3
Name: reaction_query
Version: 0.3.1
